setup.py
artipy/__init__.py
artipy/artipy.py
artipy.egg-info/PKG-INFO
artipy.egg-info/SOURCES.txt
artipy.egg-info/dependency_links.txt
artipy.egg-info/requires.txt
artipy.egg-info/top_level.txt