Metadata-Version: 1.1
Name: artipy
Version: 1.0.16
Summary: lib for adding artifact creation setup options
Home-page: UNKNOWN
Author: daniel tal
Author-email: daniel@dtsoft.co.il
License: UNKNOWN
Platform: UNKNOWN
Classifier: Programming Language :: Python :: 3
Classifier: Operating System :: OS Independent
Requires: setuptools
